{
  "openapi": "3.1.1",
  "info": {
    "title": "ResgistrationPage.api | v1",
    "version": "1.0.0"
  },
  "servers": [
    {
      "url": "https://localhost:7104"
    },
    {
      "url": "http://localhost:5018"
    }
  ],
  "paths": {
    "/api/Registration": {
      "get": {
        "tags": [
          "Registration"
        ],
        "responses": {
          "200": {
            "description": "OK"
          }
        }
      },
      "post": {
        "tags": [
          "Registration"
        ],
        "requestBody": {
          "content": {
            "application/json": {
              "schema": {
                "$ref": "#/components/schemas/Registration"
              }
            },
            "text/json": {
              "schema": {
                "$ref": "#/components/schemas/Registration"
              }
            },
            "application/*+json": {
              "schema": {
                "$ref": "#/components/schemas/Registration"
              }
            }
          },
          "required": true
        },
        "responses": {
          "200": {
            "description": "OK"
          }
        }
      }
    },
    "/api/Registration/{id}": {
      "put": {
        "tags": [
          "Registration"
        ],
        "parameters": [
          {
            "name": "id",
            "in": "path",
            "required": true,
            "schema": {
              "pattern": "^-?(?:0|[1-9]\\d*)$",
              "type": [
                "integer",
                "string"
              ],
              "format": "int32"
            }
          }
        ],
        "requestBody": {
          "content": {
            "application/json": {
              "schema": {
                "$ref": "#/components/schemas/Registration"
              }
            },
            "text/json": {
              "schema": {
                "$ref": "#/components/schemas/Registration"
              }
            },
            "application/*+json": {
              "schema": {
                "$ref": "#/components/schemas/Registration"
              }
            }
          },
          "required": true
        },
        "responses": {
          "200": {
            "description": "OK"
          }
        }
      },
      "delete": {
        "tags": [
          "Registration"
        ],
        "parameters": [
          {
            "name": "id",
            "in": "path",
            "required": true,
            "schema": {
              "pattern": "^-?(?:0|[1-9]\\d*)$",
              "type": [
                "integer",
                "string"
              ],
              "format": "int32"
            }
          }
        ],
        "responses": {
          "200": {
            "description": "OK"
          }
        }
      }
    },
    "/WeatherForecast": {
      "get": {
        "tags": [
          "WeatherForecast"
        ],
        "operationId": "GetWeatherForecast",
        "responses": {
          "200": {
            "description": "OK",
            "content": {
              "text/plain": {
                "schema": {
                  "type": "array",
                  "items": {
                    "$ref": "#/components/schemas/WeatherForecast"
                  }
                }
              },
              "application/json": {
                "schema": {
                  "type": "array",
                  "items": {
                    "$ref": "#/components/schemas/WeatherForecast"
                  }
                }
              },
              "text/json": {
                "schema": {
                  "type": "array",
                  "items": {
                    "$ref": "#/components/schemas/WeatherForecast"
                  }
                }
              }
            }
          }
        }
      }
    }
  },
  "components": {
    "schemas": {
      "Registration": {
        "required": [
          "studName",
          "mobileNo",
          "email"
        ],
        "type": "object",
        "properties": {
          "studentId": {
            "pattern": "^-?(?:0|[1-9]\\d*)$",
            "type": [
              "integer",
              "string"
            ],
            "format": "int32"
          },
          "studName": {
            "maxLength": 50,
            "type": "string"
          },
          "mobileNo": {
            "maxLength": 10,
            "type": "string"
          },
          "email": {
            "maxLength": 50,
            "type": "string"
          },
          "city": {
            "maxLength": 50,
            "type": "string"
          },
          "state": {
            "maxLength": 50,
            "type": "string"
          },
          "pincode": {
            "maxLength": 6,
            "type": "string"
          },
          "addressLine1": {
            "maxLength": 2000,
            "type": "string"
          },
          "addressLine2": {
            "maxLength": 2000,
            "type": "string"
          }
        }
      },
      "WeatherForecast": {
        "type": "object",
        "properties": {
          "date": {
            "type": "string",
            "format": "date"
          },
          "temperatureC": {
            "pattern": "^-?(?:0|[1-9]\\d*)$",
            "type": [
              "integer",
              "string"
            ],
            "format": "int32"
          },
          "temperatureF": {
            "pattern": "^-?(?:0|[1-9]\\d*)$",
            "type": [
              "integer",
              "string"
            ],
            "format": "int32"
          },
          "summary": {
            "type": [
              "null",
              "string"
            ]
          }
        }
      }
    }
  },
  "tags": [
    {
      "name": "Registration"
    },
    {
      "name": "WeatherForecast"
    }
  ]
}